{
  "users": [
    {
      "categoryid": 1, 
      "categoryname": "Dogs", 
      "dateadded": "Sun, 21 Apr 2019 16:19:38 GMT", 
      "description": "Dog breeds", 
      "userid": 1
    }, 
    {
      "categoryid": 2, 
      "categoryname": "Cats", 
      "dateadded": "Sun, 21 Apr 2019 16:19:38 GMT", 
      "description": "Cat breeds", 
      "userid": 1
    }, 
    {
      "categoryid": 3, 
      "categoryname": "Birds", 
      "dateadded": "Sun, 21 Apr 2019 16:19:38 GMT", 
      "description": "Bird breeds", 
      "userid": 1
    }, 
    {
      "categoryid": 4, 
      "categoryname": "Frogs", 
      "dateadded": "Sun, 21 Apr 2019 16:19:38 GMT", 
      "description": "Kinds of Frogs", 
      "userid": 2
    }, 
    {
      "categoryid": 5, 
      "categoryname": "Lizards", 
      "dateadded": "Sun, 21 Apr 2019 16:19:38 GMT", 
      "description": "Kinds of Lizards", 
      "userid": 2
    }, 
    {
      "categoryid": 6, 
      "categoryname": "Horses", 
      "dateadded": "Sun, 21 Apr 2019 16:19:38 GMT", 
      "description": "Types of Horses", 
      "userid": 3
    }
  ]
}
